[{"model": "rates.ratesource", "pk": 1, "fields": {"name": "muruga", "location": "vellore", "tax_included": false}}, {"model": "rates.ratesource", "pk": 2, "fields": {"name": "balwanth", "location": "vellore", "tax_included": false}}, {"model": "rates.ratesource", "pk": 3, "fields": {"name": "sbr", "location": "vellore", "tax_included": false}}, {"model": "rates.ratesource", "pk": 4, "fields": {"name": "ponnusami", "location": "vellore", "tax_included": false}}, {"model": "rates.ratesource", "pk": 5, "fields": {"name": "vt", "location": "chennai", "tax_included": false}}, {"model": "rates.rate", "pk": 1, "fields": {"metal": "Gold", "currency": "INR", "purity": "24k", "buying_rate": "6350.00", "selling_rate": "6360.00", "timestamp": "2024-02-16T08:22:20.543Z", "rate_source": 1}}, {"model": "rates.rate", "pk": 2, "fields": {"metal": "Silver", "currency": "INR", "purity": "24k", "buying_rate": "75.00", "selling_rate": "76.00", "timestamp": "2024-02-16T08:22:30.962Z", "rate_source": 1}}]